ria_remote/__init__.py
ria_remote/_version.py
ria_remote/archive2riastore.py
ria_remote/export_archive.py
ria_remote/fetch.py
ria_remote/install.py
ria_remote/remote.py
ria_remote/remote_shell_test.py
ria_remote/stage_archive.py
ria_remote/test.py
ria_remote/tests/__init__.py
ria_remote/tests/test_basics.py
ria_remote/tests/test_config.py
ria_remote/tests/test_git_remote.py
ria_remote/tests/test_gitannex.py
ria_remote/tests/utils.py
ria_remote-0.7.data/scripts/git-annex-remote-ria
ria_remote-0.7.dist-info/LICENSE
ria_remote-0.7.dist-info/METADATA
ria_remote-0.7.dist-info/WHEEL
ria_remote-0.7.dist-info/entry_points.txt
ria_remote-0.7.dist-info/top_level.txt
ria_remote-0.7.dist-info/RECORD
