Metadata-Version: 2.1
Name: ria-remote
Version: 0.7
Summary: Git-annex special remote implementation for (remote) indexed archives
Home-page: https://github.com/datalad/git-annex-ria-remote
Author: Benjamin Poldrack
Author-email: benjaminpoldrack@gmail.com
Maintainer: Benjamin Poldrack
Maintainer-email: benjaminpoldrack@gmail.com
License: MIT
Platform: UNKNOWN
Classifier: Programming Language :: Python
Classifier: License :: OSI Approved :: BSD License
Classifier: Programming Language :: Python :: 3
Requires-Python: >=3.5
Requires-Dist: annexremote
Requires-Dist: datalad (>=0.12.0rc6)
Requires-Dist: future
